mobilizon_reshare/.secrets.toml
mobilizon_reshare/VERSION
mobilizon_reshare/__init__.py
mobilizon_reshare/cli/__init__.py
mobilizon_reshare/cli/cli.py
mobilizon_reshare/cli/commands/__init__.py
mobilizon_reshare/cli/commands/format/__init__.py
mobilizon_reshare/cli/commands/format/format.py
mobilizon_reshare/cli/commands/list/__init__.py
mobilizon_reshare/cli/commands/list/list_event.py
mobilizon_reshare/cli/commands/list/list_publication.py
mobilizon_reshare/cli/commands/publish/__init__.py
mobilizon_reshare/cli/commands/publish/main.py
mobilizon_reshare/cli/commands/pull/__init__.py
mobilizon_reshare/cli/commands/pull/main.py
mobilizon_reshare/cli/commands/recap/__init__.py
mobilizon_reshare/cli/commands/recap/main.py
mobilizon_reshare/cli/commands/retry/__init__.py
mobilizon_reshare/cli/commands/retry/main.py
mobilizon_reshare/cli/commands/start/__init__.py
mobilizon_reshare/cli/commands/start/main.py
mobilizon_reshare/config/__init__.py
mobilizon_reshare/config/command.py
mobilizon_reshare/config/config.py
mobilizon_reshare/config/notifiers.py
mobilizon_reshare/config/publishers.py
mobilizon_reshare/config/strategies.py
mobilizon_reshare/dataclasses/__init__.py
mobilizon_reshare/dataclasses/event.py
mobilizon_reshare/dataclasses/event_publication_status.py
mobilizon_reshare/dataclasses/publication.py
mobilizon_reshare/event/__init__.py
mobilizon_reshare/event/event_selection_strategies.py
mobilizon_reshare/formatting/__init__.py
mobilizon_reshare/formatting/description.py
mobilizon_reshare/main/__init__.py
mobilizon_reshare/main/publish.py
mobilizon_reshare/main/pull.py
mobilizon_reshare/main/recap.py
mobilizon_reshare/main/retry.py
mobilizon_reshare/main/start.py
mobilizon_reshare/migrations/postgres/models/0_20221006223256_init.sql
mobilizon_reshare/migrations/postgres/pyproject.toml
mobilizon_reshare/migrations/sqlite/models/0_20211207110159_init.sql
mobilizon_reshare/migrations/sqlite/models/1_20211218165547_add column last_update_time for event.sql
mobilizon_reshare-0.3.6.dist-info/entry_points.txt
mobilizon_reshare-0.3.6.dist-info/LICENSE
mobilizon_reshare-0.3.6.dist-info/WHEEL
mobilizon_reshare-0.3.6.dist-info/METADATA
mobilizon_reshare-0.3.6.dist-info/RECORD
