Metadata-Version: 2.1
Name: mobilizon-reshare
Version: 0.3.6
Summary: A suite to reshare Mobilizon events on a broad selection of platforms
Home-page: https://github.com/Tech-Workers-Coalition-Italia/mobilizon-reshare
License: Coopyleft
Author: Simone Robutti
Author-email: simone.robutti@protonmail.com
Requires-Python: >=3.9,<4.0
Classifier: License :: Other/Proprietary License
Classifier: Programming Language :: Python :: 3
Classifier: Programming Language :: Python :: 3.10
Classifier: Programming Language :: Python :: 3.9
Requires-Dist: Jinja2 (>=3.1,<3.2)
Requires-Dist: aerich (>=0.6,<0.7)
Requires-Dist: aiosqlite (>=0.17,<0.18)
Requires-Dist: appdirs (>=1.4,<1.5)
Requires-Dist: arrow (>=1.1,<1.2)
Requires-Dist: beautifulsoup4 (>=4.11,<4.12)
Requires-Dist: click (>=8.1,<8.2)
Requires-Dist: dynaconf (>=3.1,<3.2)
Requires-Dist: facebook-sdk (>=3.1,<3.2)
Requires-Dist: fastapi (>=0.85,<0.86)
Requires-Dist: fastapi-pagination (>=0.11.0,<0.12.0)
Requires-Dist: markdownify (>=0.10,<0.11)
Requires-Dist: requests (>=2.28,<2.29)
Requires-Dist: tortoise-orm[asyncpg] (>=0.19,<0.20)
Requires-Dist: tweepy (>=4.13,<4.14)
Requires-Dist: uvicorn (>=0.17,<0.18)
Project-URL: Repository, https://github.com/Tech-Workers-Coalition-Italia/mobilizon-reshare
